MKLpy/__init__.py
MKLpy/arrange.py
MKLpy/multiclass.py
MKLpy/weights.py
MKLpy/algorithms/AlternateMKL.py
MKLpy/algorithms/AverageMKL.py
MKLpy/algorithms/EasyMKL.py
MKLpy/algorithms/MEMO.py
MKLpy/algorithms/__init__.py
MKLpy/algorithms/base.py
MKLpy/algorithms/komd.py
MKLpy/lists/__init__.py
MKLpy/lists/generator.py
MKLpy/lists/kernel_list.py
MKLpy/metrics/__init__.py
MKLpy/metrics/alignment.py
MKLpy/metrics/evaluate.py
MKLpy/metrics/pairwise/__init__.py
MKLpy/metrics/pairwise/boolean.py
MKLpy/metrics/pairwise/misc.py
MKLpy/metrics/pairwise/string.py
MKLpy/model_selection/__init__.py
MKLpy/model_selection/splits.py
MKLpy/model_selection/validation.py
MKLpy/preprocessing/__init__.py
MKLpy/preprocessing/binarization.py
MKLpy/preprocessing/data_preprocessing.py
MKLpy/preprocessing/kernel_preprocessing.py
MKLpy/preprocessing/relaxation.py
MKLpy/utils/__init__.py
MKLpy/utils/exceptions.py
MKLpy/utils/matrices.py
MKLpy/utils/mkl_checks.py
MKLpy/utils/validation.py
MKLpy-0.3.2.dist-info/LICENSE
MKLpy-0.3.2.dist-info/METADATA
MKLpy-0.3.2.dist-info/WHEEL
MKLpy-0.3.2.dist-info/top_level.txt
MKLpy-0.3.2.dist-info/RECORD
