Metadata-Version: 1.1
Name: MKLpy
Version: 0.3.2
Summary: A package for Multiple Kernel Learning scikit-compliant
Home-page: https://github.com/IvanoLauriola/MKLpy
Author: Lauriola Ivano
Author-email: ivano.lauriola@phd.unipd.it
License: GNU General Public License v3.0
Download-URL: https://github.com/IvanoLauriola/MKLpy
Keywords: kernel,MKL,learning,multiple kernel learning,EasyMKL,SVM,boolean kernels
Platform: UNKNOWN
Classifier: Development Status :: 3 - Alpha
Classifier: Programming Language :: Python :: 3.6
Classifier: Topic :: Scientific/Engineering :: Artificial Intelligence
Classifier: Topic :: Scientific/Engineering :: Mathematics
